{"pageId":"fe82c080402a2cb5","url":"https://www.cdc.gov/spanish/niosh/hhe/hhe-info.html","week":"2026-W29","runId":"2026-07-14T10-24-15-493Z-025de7","scannedAt":"2026-07-14T10:55:15.231Z","status":200,"depth":5,"axe":{"engine":"axe-core","version":"4.12.1","violationCount":7,"violations":{"image-redundant-alt":{"count":1,"impact":"minor","help":"Alternative text of images should not be repeated as text","helpUrl":"https://dequeuniversity.com/rules/axe/4.12/image-redundant-alt?application=axeAPI","tags":["best-practice"],"examples":[{"target":"img[title=\"hhe7.jpg_8c55c\"]","html":"<img decoding=\"async\" class=\"card-img-top img-fluid img-fluid\" alt=\"Trabajador barriendo pisos en una planta de fabricación de láminas de fibra.\" title=\"hhe7.jpg_8c55c\" src=\"/spanish/niosh/hhe/images/"}]},"region":{"count":6,"impact":"moderate","help":"All page content should be contained by landmarks","helpUrl":"https://dequeuniversity.com/rules/axe/4.12/region?application=axeAPI","tags":["best-practice"],"examples":[{"target":"small","html":"<small class=\"ml-2\">Un sitio oficial del Gobierno de Estados Unidos <button class=\"cdc-header-official-notice-header-btn\">Así es como usted puede verificarlo <span class=\"cdc-header-official-notice-he"},{"target":".card-header.h4","html":"<div class=\"card-header h4\"><span class=\"fi cdc-icon-email_03 icon x32\"></span><span class=\"gov-d-header-text\">Reciba actualizaciones por correo electrónico</span></div>"},{"target":".tp-gov-d > .card-body > p","html":"<p>Para recibir actualizaciones de esta página, ingrese su correo electrónico:</p>"}]}},"incompleteCount":2},"alfa":{"engine":"alfa","version":"0.117.0","failedCount":50,"failed":{"sia-r66":{"count":10,"ruleUrl":"https://alfa.siteimprove.com/rules/sia-r66","examples":[{"target":"text: \"Un sitio oficial del Gobierno de Estados Unidos \""},{"target":"text: \"Así es como usted puede verificarlo \""},{"target":"text: \"¿Qué es una Evaluación de riesgos para la salud?\""}]},"sia-r14":{"count":1,"ruleUrl":"https://alfa.siteimprove.com/rules/sia-r14","examples":[{"target":"<a href=\"#print\" class=\"print-link\" aria-label=\"print this page\" onclick=\"window.print()\">"}]},"sia-r113":{"count":1,"ruleUrl":"https://alfa.siteimprove.com/rules/sia-r113","examples":[{"target":"<a href=\"#nav-group-cdceb\" aria-controls=\"nav-group-cdceb\" class=\"nav-plus nav-expandcollapse\" data-toggle=\"collapse\">"}]},"sia-r57":{"count":14,"ruleUrl":"https://alfa.siteimprove.com/rules/sia-r57","examples":[{"target":"text: \"Skip directly to search\""},{"target":"text: \"Un sitio oficial del Gobierno de Estados Unidos \""},{"target":"text: \"Así es como usted puede verificarlo \""}]},"sia-r111":{"count":24,"ruleUrl":"https://alfa.siteimprove.com/rules/sia-r111","examples":[{"target":"<a href=\"/niosh/hhe/HHEprogram.html\">"},{"target":"<a href=\"#print\" class=\"print-link\" aria-label=\"print this page\" onclick=\"window.print()\">"},{"target":"<a href=\"#whatis\">"}]}},"cantTellCount":4,"passedRules":33},"resources":{"engine":"resources","count":0,"byType":{},"resources":[]},"images":{"engine":"images","count":16,"images":[{"src":"https://www.cdc.gov/TemplatePackage/4.0/assets/imgs/uswds/us_flag_small.png","alt":"","hasAlt":true,"isDecorative":true,"isMissingAlt":false,"ariaHidden":true,"rolePresentation":false,"renderedWidth":16,"renderedHeight":11,"naturalWidth":64,"naturalHeight":44,"loading":null,"decoding":null,"altVerdict":"DECORATIVE","altReason":"aria-hidden=\"true\"","bytes":545},{"src":"https://www.cdc.gov/TemplatePackage/4.0/assets/imgs/uswds/icon-dot-gov.svg","alt":"","hasAlt":true,"isDecorative":true,"isMissingAlt":false,"ariaHidden":true,"rolePresentation":false,"renderedWidth":150,"renderedHeight":150,"naturalWidth":150,"naturalHeight":150,"loading":null,"decoding":null,"altVerdict":"DECORATIVE","altReason":"aria-hidden=\"true\"","bytes":377},{"src":"https://www.cdc.gov/TemplatePackage/4.0/assets/imgs/uswds/icon-https.svg","alt":"","hasAlt":true,"isDecorative":true,"isMissingAlt":false,"ariaHidden":true,"rolePresentation":false,"renderedWidth":150,"renderedHeight":150,"naturalWidth":150,"naturalHeight":150,"loading":null,"decoding":null,"altVerdict":"DECORATIVE","altReason":"aria-hidden=\"true\"","bytes":325},{"src":"https://www.cdc.gov/TemplatePackage/4.0/assets/imgs/logo/logo-notext.svg","alt":"CDC Logo","hasAlt":true,"isDecorative":false,"isMissingAlt":false,"ariaHidden":false,"rolePresentation":false,"renderedWidth":125,"renderedHeight":60,"naturalWidth":233,"naturalHeight":150,"loading":null,"decoding":null,"altVerdict":"GOOD","altReason":"present, no red flags","bytes":1262},{"src":"https://www.cdc.gov/TemplatePackage/4.0/assets/imgs/logo/logo-notext.svg","alt":"CDC Logo","hasAlt":true,"isDecorative":false,"isMissingAlt":false,"ariaHidden":false,"rolePresentation":false,"renderedWidth":233,"renderedHeight":150,"naturalWidth":233,"naturalHeight":150,"loading":null,"decoding":null,"altVerdict":"GOOD","altReason":"present, no red flags","bytes":1262},{"src":"https://www.cdc.gov/spanish/niosh/hhe/images/hhe1.gif?_=10998","alt":"Personal de NIOSH escribiendo","hasAlt":true,"isDecorative":false,"isMissingAlt":false,"ariaHidden":false,"rolePresentation":false,"renderedWidth":75,"renderedHeight":65,"naturalWidth":75,"naturalHeight":65,"loading":null,"decoding":"async","altVerdict":"GOOD","altReason":"present, no red flags","bytes":4407},{"src":"https://www.cdc.gov/spanish/niosh/hhe/images/hhe2.jpg?_=10996","alt":"Personal de NIOSH llamando por teléfono","hasAlt":true,"isDecorative":false,"isMissingAlt":false,"ariaHidden":false,"rolePresentation":false,"renderedWidth":75,"renderedHeight":62,"naturalWidth":75,"naturalHeight":62,"loading":null,"decoding":"async","altVerdict":"GOOD","altReason":"present, no red flags","bytes":2391},{"src":"https://www.cdc.gov/spanish/niosh/hhe/images/hhe3.jpg?_=11009","alt":"El personal de NIOSH prueba el ajuste de un respirador","hasAlt":true,"isDecorative":false,"isMissingAlt":false,"ariaHidden":false,"rolePresentation":false,"renderedWidth":75,"renderedHeight":72,"naturalWidth":75,"naturalHeight":72,"loading":null,"decoding":"async","altVerdict":"GOOD","altReason":"present, no red flags","bytes":2195},{"src":"https://www.cdc.gov/spanish/niosh/hhe/images/hhe4.jpg?_=11003","alt":"Trabajadores cortando carnes en un matadero.","hasAlt":true,"isDecorative":false,"isMissingAlt":false,"ariaHidden":false,"rolePresentation":false,"renderedWidth":160,"renderedHeight":158,"naturalWidth":157,"naturalHeight":155,"loading":null,"decoding":"async","altVerdict":"GOOD","altReason":"present, no red flags","bytes":6334},{"src":"https://www.cdc.gov/spanish/niosh/hhe/images/hhe5.jpg?_=11008","alt":"Trabajador cortando piezas de metal con soplete.","hasAlt":true,"isDecorative":false,"isMissingAlt":false,"ariaHidden":false,"rolePresentation":false,"renderedWidth":160,"renderedHeight":120,"naturalWidth":180,"naturalHeight":135,"loading":null,"decoding":"async","altVerdict":"GOOD","altReason":"present, no red flags","bytes":6316},{"src":"https://www.cdc.gov/spanish/niosh/hhe/images/hhe6.jpg?_=10999","alt":"Personal de NIOSH midiendo la exposición a la radiación.","hasAlt":true,"isDecorative":false,"isMissingAlt":false,"ariaHidden":false,"rolePresentation":false,"renderedWidth":160,"renderedHeight":177,"naturalWidth":130,"naturalHeight":144,"loading":null,"decoding":"async","altVerdict":"GOOD","altReason":"present, no red flags","bytes":5469},{"src":"https://www.cdc.gov/spanish/niosh/hhe/images/hhe7.jpg?_=11007","alt":"Trabajador barriendo pisos en una planta de fabricación de láminas de fibra.","hasAlt":true,"isDecorative":false,"isMissingAlt":false,"ariaHidden":false,"rolePresentation":false,"renderedWidth":150,"renderedHeight":135,"naturalWidth":150,"naturalHeight":135,"loading":null,"decoding":"async","altVerdict":"GOOD","altReason":"present, no red flags","bytes":4263},{"src":"https://www.cdc.gov/spanish/niosh/hhe/images/hhe8.jpg?_=11000","alt":"Trabajadores instalando un aislamiento de celulosa.","hasAlt":true,"isDecorative":false,"isMissingAlt":false,"ariaHidden":false,"rolePresentation":false,"renderedWidth":160,"renderedHeight":131,"naturalWidth":171,"naturalHeight":140,"loading":null,"decoding":"async","altVerdict":"GOOD","altReason":"present, no red flags","bytes":4448},{"src":"https://www.cdc.gov/spanish/niosh/hhe/images/hhe10.jpg?_=11005","alt":"Agentes del orden público practicando en un campo de tiro.","hasAlt":true,"isDecorative":false,"isMissingAlt":false,"ariaHidden":false,"rolePresentation":false,"renderedWidth":160,"renderedHeight":121,"naturalWidth":160,"naturalHeight":121,"loading":null,"decoding":"async","altVerdict":"GOOD","altReason":"present, no red flags","bytes":4924},{"src":"https://www.cdc.gov/TemplatePackage/5.0/img/logo/cdc-logo-tag-right.svg","alt":"Centros para la Salud y el Desarrollo Humano","hasAlt":true,"isDecorative":false,"isMissingAlt":false,"ariaHidden":false,"rolePresentation":false,"renderedWidth":283,"renderedHeight":66,"naturalWidth":827,"naturalHeight":193,"loading":null,"decoding":null,"altVerdict":"GOOD","altReason":"present, no red flags","bytes":4780},{"src":"https://www.cdc.gov/TemplatePackage/contrib/libs/cdc/c2r/crlogo.svg","alt":"Content Credentials logo","hasAlt":true,"isDecorative":false,"isMissingAlt":false,"ariaHidden":false,"rolePresentation":false,"renderedWidth":25,"renderedHeight":150,"naturalWidth":150,"naturalHeight":150,"loading":null,"decoding":null,"altVerdict":"GOOD","altReason":"present, no red flags","bytes":1490}]}}