{"pageId":"7704a35b7ea9b107","url":"https://www.medicaid.gov/medicaid/quality-of-care/quality-improvement-initiatives/index.html","week":"2026-W30","runId":"2026-07-22T05-32-04-814Z-a399db","scannedAt":"2026-07-22T05:50:01.701Z","status":200,"depth":5,"axe":{"engine":"axe-core","version":"4.12.1","violationCount":0,"violations":{},"incompleteCount":2},"resources":{"engine":"resources","count":18,"byType":{"pdf":3,"document":14,"archive":1},"resources":[{"url":"https://www.medicaid.gov/federal-policy-guidance/downloads/cib052423.pdf","type":"pdf"},{"url":"https://www.medicaid.gov/medicaid/quality-of-care/downloads/drvr-digrm-chng-idea-table.pdf","type":"pdf"},{"url":"https://www.medicaid.gov/medicaid/quality-of-care/downloads/aim-statement.docx","type":"document"},{"url":"https://www.medicaid.gov/medicaid/quality-of-care/downloads/driver-diagram.docx","type":"document"},{"url":"https://www.medicaid.gov/medicaid/quality-of-care/downloads/process-flow.docx","type":"document"},{"url":"https://www.medicaid.gov/medicaid/quality-of-care/downloads/team-matrix.docx","type":"document"},{"url":"https://www.medicaid.gov/medicaid/quality-of-care/downloads/pdsa-wkst.docx","type":"document"},{"url":"https://www.medicaid.gov/medicaid/quality-of-care/downloads/pdsa-series-wkst.docx","type":"document"},{"url":"https://www.medicaid.gov/medicaid/quality-of-care/downloads/msurmnt-strtgy.pdf","type":"pdf"},{"url":"https://www.medicaid.gov/medicaid/quality-of-care/downloads/measure-strat.docx","type":"document"},{"url":"https://www.medicaid.gov/medicaid/quality-of-care/downloads/how-to-runchart.docx","type":"document"},{"url":"https://www.medicaid.gov/medicaid/quality-of-care/downloads/imp-sustainability.docx","type":"document"},{"url":"https://www.medicaid.gov/medicaid/quality-of-care/downloads/spread-qi.docx","type":"document"},{"url":"https://www.medicaid.gov/medicaid/quality-of-care/downloads/qi-partner-engage-guide.docx","type":"document"},{"url":"https://www.medicaid.gov/medicaid/quality-of-care/downloads/qi-coordination-planner.docx","type":"document"},{"url":"https://www.medicaid.gov/medicaid/quality-of-care/downloads/storyboard-temp.docx","type":"document"},{"url":"https://www.medicaid.gov/medicaid/quality-of-care/downloads/craft-key-messages.docx","type":"document"},{"url":"https://www.medicaid.gov/medicaid/quality-of-care/downloads/qi-worksheets.zip","type":"archive"}]},"images":{"engine":"images","count":10,"images":[{"src":"https://www.medicaid.gov/themes/custom/medicaid/dist/img/us_flag_small.png","alt":"","hasAlt":true,"isDecorative":true,"isMissingAlt":false,"ariaHidden":true,"rolePresentation":false,"renderedWidth":16,"renderedHeight":11,"naturalWidth":64,"naturalHeight":44,"loading":null,"decoding":null,"altVerdict":"DECORATIVE","altReason":"aria-hidden=\"true\"","bytes":244},{"src":"https://www.medicaid.gov/themes/custom/medicaid/dist/img/icon-dot-gov.svg","alt":"","hasAlt":true,"isDecorative":true,"isMissingAlt":false,"ariaHidden":true,"rolePresentation":false,"renderedWidth":64,"renderedHeight":64,"naturalWidth":64,"naturalHeight":64,"loading":null,"decoding":null,"altVerdict":"DECORATIVE","altReason":"aria-hidden=\"true\"","bytes":324},{"src":"https://www.medicaid.gov/themes/custom/medicaid/dist/img/icon-https.svg","alt":"","hasAlt":true,"isDecorative":true,"isMissingAlt":false,"ariaHidden":true,"rolePresentation":false,"renderedWidth":64,"renderedHeight":64,"naturalWidth":64,"naturalHeight":64,"loading":null,"decoding":null,"altVerdict":"DECORATIVE","altReason":"aria-hidden=\"true\"","bytes":344},{"src":"https://www.medicaid.gov/themes/custom/medicaid/images/logo/medicaid_logo_green.svg","alt":"Medicaid.gov-Keeping America Healthy","hasAlt":true,"isDecorative":false,"isMissingAlt":false,"ariaHidden":false,"rolePresentation":false,"renderedWidth":302,"renderedHeight":61,"naturalWidth":300,"naturalHeight":61,"loading":null,"decoding":null,"altVerdict":"GOOD","altReason":"present, no red flags","bytes":2850},{"src":"https://www.medicaid.gov/themes/custom/medicaid/dist/img/usa-icons-bg/search--white.svg","alt":"Search","hasAlt":true,"isDecorative":false,"isMissingAlt":false,"ariaHidden":false,"rolePresentation":false,"renderedWidth":24,"renderedHeight":24,"naturalWidth":24,"naturalHeight":24,"loading":null,"decoding":null,"altVerdict":"GOOD","altReason":"present, no red flags","bytes":224},{"src":"https://www.medicaid.gov/themes/custom/medicaid/dist/img/usa-icons/close.svg","alt":"Close","hasAlt":true,"isDecorative":false,"isMissingAlt":false,"ariaHidden":false,"rolePresentation":false,"renderedWidth":24,"renderedHeight":24,"naturalWidth":24,"naturalHeight":24,"loading":null,"decoding":null,"altVerdict":"GOOD","altReason":"present, no red flags","bytes":128},{"src":"https://www.medicaid.gov/themes/custom/medicaid/dist/img/usa-icons-bg/search--white.svg","alt":"Search","hasAlt":true,"isDecorative":false,"isMissingAlt":false,"ariaHidden":false,"rolePresentation":false,"renderedWidth":24,"renderedHeight":24,"naturalWidth":24,"naturalHeight":24,"loading":null,"decoding":null,"altVerdict":"GOOD","altReason":"present, no red flags","bytes":224},{"src":"https://www.medicaid.gov/sites/default/files/2026-02/phase%201-4.png","alt":"Phases 1 - 4 Improving Quality of Care Image","hasAlt":true,"isDecorative":false,"isMissingAlt":false,"ariaHidden":false,"rolePresentation":false,"renderedWidth":582,"renderedHeight":271,"naturalWidth":2162,"naturalHeight":1005,"loading":"lazy","decoding":null,"altVerdict":"GOOD","altReason":"present, no red flags","bytes":33237},{"src":"https://www.medicaid.gov/sites/default/files/2026-02/act-plan-image_1.png","alt":"Act Plan Diagram Image","hasAlt":true,"isDecorative":false,"isMissingAlt":false,"ariaHidden":false,"rolePresentation":false,"renderedWidth":211,"renderedHeight":222,"naturalWidth":211,"naturalHeight":222,"loading":"lazy","decoding":null,"altVerdict":"GOOD","altReason":"present, no red flags","bytes":4218},{"src":"https://www.medicaid.gov/themes/custom/medicaid/images/logo/medicaid_logo_green.svg","alt":"Medicaid.gov: Keeping America Healthy","hasAlt":true,"isDecorative":false,"isMissingAlt":false,"ariaHidden":false,"rolePresentation":false,"renderedWidth":228,"renderedHeight":46,"naturalWidth":300,"naturalHeight":61,"loading":null,"decoding":null,"altVerdict":"GOOD","altReason":"present, no red flags","bytes":2850}]},"tech":[{"name":"Chartbeat","category":"Analytics","categories":["Analytics"],"confidence":100,"version":null,"website":"https://chartbeat.com","cpe":null},{"name":"Google Analytics","category":"Analytics","categories":["Analytics"],"confidence":100,"version":null,"website":"https://google.com/analytics","cpe":null},{"name":"cdnjs","category":"CDN","categories":["CDN"],"confidence":100,"version":null,"website":"https://cdnjs.com","cpe":null},{"name":"Cloudflare","category":"CDN","categories":["CDN"],"confidence":100,"version":null,"website":"https://www.cloudflare.com","cpe":null},{"name":"jsDelivr","category":"CDN","categories":["CDN"],"confidence":100,"version":null,"website":"https://www.jsdelivr.com/","cpe":null},{"name":"Drupal","category":"CMS","categories":["CMS"],"confidence":100,"version":null,"website":"https://www.drupal.org/","cpe":"cpe:2.3:a:drupal:drupal:*:*:*:*:*:*:*:*"},{"name":"jQuery","category":"JavaScript libraries","categories":["JavaScript libraries"],"confidence":100,"version":null,"website":"https://jquery.com","cpe":"cpe:2.3:a:jquery:jquery:*:*:*:*:*:*:*:*"},{"name":"Select2","category":"JavaScript libraries","categories":["JavaScript libraries"],"confidence":100,"version":null,"website":"https://select2.org/","cpe":null},{"name":"Acquia Cloud Platform","category":"PaaS","categories":["PaaS"],"confidence":100,"version":null,"website":"https://www.acquia.com/products/drupal-cloud/cloud-platform","cpe":null},{"name":"Amazon Web Services","category":"PaaS","categories":["PaaS"],"confidence":100,"version":null,"website":"https://aws.amazon.com/","cpe":null},{"name":"PHP","category":"Programming languages","categories":["Programming languages"],"confidence":100,"version":null,"website":"https://php.net","cpe":"cpe:2.3:a:php:php:*:*:*:*:*:*:*:*"},{"name":"HSTS","category":"Security","categories":["Security"],"confidence":100,"version":null,"website":"https://www.rfc-editor.org/rfc/rfc6797#section-6.1","cpe":null},{"name":"Qualtrics","category":"Surveys","categories":["Surveys"],"confidence":100,"version":null,"website":"https://www.qualtrics.com","cpe":null},{"name":"Tealium","category":"Tag managers","categories":["Tag managers","Customer data platform"],"confidence":100,"version":null,"website":"https://tealium.com","cpe":null},{"name":"USWDS","category":"UI frameworks","categories":["UI frameworks"],"confidence":100,"version":null,"website":"https://designsystem.digital.gov","cpe":null}],"thirdParty":{"engine":"third-party","pageUrl":"https://www.medicaid.gov/medicaid/quality-of-care/quality-improvement-initiatives/index.html","thirdPartyOrigins":9,"scriptOrigins":8,"totalThirdPartyRequests":32,"totalThirdPartyBytes":1205975,"totalThirdPartyScripts":24,"firstPartyRequests":83,"firstPartyBytes":595239,"origins":[{"origin":"qualtrics.com","requests":14,"bytes":849475,"scripts":9,"byType":{"script":9,"xhr":4,"fetch":1},"totalDurationMs":559},{"origin":"googletagmanager.com","requests":1,"bytes":156084,"scripts":1,"byType":{"script":1},"totalDurationMs":2},{"origin":"jsdelivr.net","requests":6,"bytes":53126,"scripts":4,"byType":{"stylesheet":1,"script":4,"xhr":1},"totalDurationMs":296},{"origin":"chartbeat.com","requests":1,"bytes":40167,"scripts":1,"byType":{"script":1},"totalDurationMs":1},{"origin":"cloudflare.com","requests":2,"bytes":31878,"scripts":2,"byType":{"script":2},"totalDurationMs":145},{"origin":"digitalgov.gov","requests":1,"bytes":30230,"scripts":1,"byType":{"script":1},"totalDurationMs":1},{"origin":"tiqcdn.com","requests":5,"bytes":24789,"scripts":5,"byType":{"script":5},"totalDurationMs":15},{"origin":"adoberesources.net","requests":1,"bytes":20183,"scripts":1,"byType":{"script":1},"totalDurationMs":1},{"origin":"chartbeat.net","requests":1,"bytes":43,"scripts":0,"byType":{"image":1},"totalDurationMs":73}]}}