{"pageId":"ab72883b7144b520","url":"https://www.cdc.gov/heat-health/hcp/clinical-guidance/references.html","week":"2026-W28","runId":"2026-07-06T10-13-27-433Z-ef4571","scannedAt":"2026-07-06T11:17:15.689Z","status":200,"depth":4,"axe":{"engine":"axe-core","version":"4.12.1","violationCount":5,"violations":{"landmark-unique":{"count":1,"impact":"moderate","help":"Landmarks should have a unique role or role/label/title (i.e. accessible name) combination","helpUrl":"https://dequeuniversity.com/rules/axe/4.12/landmark-unique?application=axeAPI","tags":["best-practice"],"examples":[{"target":".page-right-rail__static","html":"<aside class=\"page-right-rail__static noindex\" role=\"complementary\" style=\"margin-top: 47px;\">"}]},"region":{"count":4,"impact":"moderate","help":"All page content should be contained by landmarks","helpUrl":"https://dequeuniversity.com/rules/axe/4.12/region?application=axeAPI","tags":["best-practice"],"examples":[{"target":".cdc-site-gov-notice","html":"<div class=\"cdc-site-gov-notice noindex noprint\" aria-label=\"Official website of the United States government\">"},{"target":".site-footer__heading","html":"<div class=\"col-lg-3 site-footer__heading\n\t\t\t\t\t\">"},{"target":".site-footer__links","html":"<div class=\"row site-footer__links\">"}]}},"incompleteCount":25},"alfa":{"engine":"alfa","version":"0.117.0","failedCount":446,"failed":{"sia-r66":{"count":184,"ruleUrl":"https://alfa.siteimprove.com/rules/sia-r66","examples":[{"target":"text: \"\n\t\t\t\t\tHere's how you know\n\t\t\t\t\t\""},{"target":"text: \"\n\t\t\t\t\t\tExplore This Topic\t\t\t\t\t\""},{"target":"text: \"Search\""}]},"sia-r68":{"count":178,"ruleUrl":"https://alfa.siteimprove.com/rules/sia-r68","examples":[{"target":"<ol>"},{"target":"<ol>"},{"target":"<ol>"}]},"sia-r18":{"count":1,"ruleUrl":"https://alfa.siteimprove.com/rules/sia-r18","examples":[{"target":"@aria-label=\"Official website of the United States government\""}]},"sia-r57":{"count":15,"ruleUrl":"https://alfa.siteimprove.com/rules/sia-r57","examples":[{"target":"text: \"Skip directly to search\""},{"target":"text: \"Skip directly to On This Page\""},{"target":"text: \"An official website of the United States government\""}]},"sia-r69":{"count":6,"ruleUrl":"https://alfa.siteimprove.com/rules/sia-r69","examples":[{"target":"text: \"Related Pages\""},{"target":"text: \"Clinical Guidance\""},{"target":"text: \"Quick Start Guide for Clinicians on Heat and Health\""}]},"sia-r111":{"count":62,"ruleUrl":"https://alfa.siteimprove.com/rules/sia-r111","examples":[{"target":"<button class=\"btn btn-outline-white btn-arrow-down btn-fancy\" id=\"megaButton\">"},{"target":"<button id=\"cdc-search__toggle\" aria-controls=\"cdc-header__search-inner\" type=\"button\">"},{"target":"<a href=\"https://cdc-my.sharepoint.com/personal/lvs3_cdc_gov/Documents/+My_Large_Workspace/NCEH%20Sr%20Med%20Adv/Heat%20Initiative/HEAT.gov%20-%20National%20Integrated%20Heat%20Health%20Information%20"}]}},"cantTellCount":2,"passedRules":32},"resources":{"engine":"resources","count":6,"byType":{"pdf":5,"image":1},"resources":[{"url":"https://www.epa.gov/system/files/documents/2023-05/Climate_Change_and_Children%27s_Health_Report_Executive_Summary_.pdf","type":"pdf"},{"url":"https://www.cdc.gov/niosh/docs/2016-106/pdfs/2016-106.pdf?id=10.26616/NIOSHPUB2016106","type":"pdf"},{"url":"https://www.cdc.gov/asthma/media/pdfs/2024/06/home_assess_checklist_p.pdf","type":"pdf"},{"url":"https://www.cdc.gov/air-quality/media/air_quality_and_outdoor_activity_guidance.pdf","type":"pdf"},{"url":"https://www.weather.gov/images/wrn/Infographics/2022/heat-symptoms-2022-final.png","type":"image"},{"url":"https://www.cdc.gov/asthma/action-plan/documents/asthma-action-plan-508.pdf","type":"pdf"}]},"images":{"engine":"images","count":6,"images":[{"src":"https://www.cdc.gov/TemplatePackage/5.0/img/uswds/us_flag_small.png","alt":"","hasAlt":true,"isDecorative":true,"isMissingAlt":false,"ariaHidden":true,"rolePresentation":false,"renderedWidth":16,"renderedHeight":11,"naturalWidth":64,"naturalHeight":44,"loading":null,"decoding":null,"altVerdict":"DECORATIVE","altReason":"aria-hidden=\"true\"","bytes":545},{"src":"https://www.cdc.gov/TemplatePackage/5.0/img/uswds/icon-dot-gov.svg","alt":"","hasAlt":true,"isDecorative":true,"isMissingAlt":false,"ariaHidden":true,"rolePresentation":false,"renderedWidth":150,"renderedHeight":150,"naturalWidth":150,"naturalHeight":150,"loading":null,"decoding":null,"altVerdict":"DECORATIVE","altReason":"aria-hidden=\"true\"","bytes":377},{"src":"https://www.cdc.gov/TemplatePackage/5.0/img/uswds/icon-https.svg","alt":"","hasAlt":true,"isDecorative":true,"isMissingAlt":false,"ariaHidden":true,"rolePresentation":false,"renderedWidth":150,"renderedHeight":150,"naturalWidth":150,"naturalHeight":150,"loading":null,"decoding":null,"altVerdict":"DECORATIVE","altReason":"aria-hidden=\"true\"","bytes":325},{"src":"https://www.cdc.gov/TemplatePackage/5.0/img/logo/logo-notext.svg","alt":"Centers for Disease Control and Prevention. CDC twenty four seven. Saving Lives, Protecting People","hasAlt":true,"isDecorative":false,"isMissingAlt":false,"ariaHidden":false,"rolePresentation":false,"renderedWidth":125,"renderedHeight":81,"naturalWidth":233,"naturalHeight":150,"loading":null,"decoding":null,"altVerdict":"GOOD","altReason":"present, no red flags","bytes":1262},{"src":"https://www.cdc.gov/TemplatePackage/5.0/img/logo/logo-notext.svg","alt":"Centers for Disease Control and Prevention. CDC twenty four seven. Saving Lives, Protecting People","hasAlt":true,"isDecorative":false,"isMissingAlt":false,"ariaHidden":false,"rolePresentation":false,"renderedWidth":233,"renderedHeight":150,"naturalWidth":233,"naturalHeight":150,"loading":null,"decoding":null,"altVerdict":"GOOD","altReason":"present, no red flags","bytes":1262},{"src":"https://www.cdc.gov/TemplatePackage/5.0/img/logo/cdc-logo-tag-right.svg","alt":"Centers for Disease Control and Prevention","hasAlt":true,"isDecorative":false,"isMissingAlt":false,"ariaHidden":false,"rolePresentation":false,"renderedWidth":282,"renderedHeight":66,"naturalWidth":827,"naturalHeight":193,"loading":null,"decoding":null,"altVerdict":"GOOD","altReason":"present, no red flags","bytes":4780}]}}