{"pageId":"c6ecd197df58abef","url":"https://www.medicaid.gov/medicaid/section-1115-demo/demonstration-and-waiver-list?items_per_page=10&page=2&sl=yes&usid=KY","week":"2026-W29","runId":"2026-07-19T07-14-39-920Z-a263b4","scannedAt":"2026-07-19T07:15:00.200Z","status":200,"depth":8,"sustainability":{"engine":"sustainability","requests":156,"bytes":1769103,"byType":{"document":20658,"stylesheet":121441,"image":5582,"script":1523866,"other":21796,"font":62216,"fetch":410,"xhr":13134},"co2g":0.2622,"energyWh":0.5307,"model":"swd-v4 (co2.js)"},"axe":{"engine":"axe-core","version":"4.12.1","violationCount":0,"violations":{},"incompleteCount":8},"resources":{"engine":"resources","count":1,"byType":{"pdf":1},"resources":[{"url":"https://www.medicaid.gov/federal-policy-guidance/downloads/cib052423.pdf","type":"pdf"}]},"images":{"engine":"images","count":9,"images":[{"src":"https://www.medicaid.gov/themes/custom/medicaid/dist/img/us_flag_small.png","alt":"","hasAlt":true,"isDecorative":true,"isMissingAlt":false,"ariaHidden":true,"rolePresentation":false,"renderedWidth":16,"renderedHeight":11,"naturalWidth":64,"naturalHeight":44,"loading":null,"decoding":null,"altVerdict":"DECORATIVE","altReason":"aria-hidden=\"true\"","bytes":244},{"src":"https://www.medicaid.gov/themes/custom/medicaid/dist/img/icon-dot-gov.svg","alt":"","hasAlt":true,"isDecorative":true,"isMissingAlt":false,"ariaHidden":true,"rolePresentation":false,"renderedWidth":64,"renderedHeight":64,"naturalWidth":64,"naturalHeight":64,"loading":null,"decoding":null,"altVerdict":"DECORATIVE","altReason":"aria-hidden=\"true\"","bytes":324},{"src":"https://www.medicaid.gov/themes/custom/medicaid/dist/img/icon-https.svg","alt":"","hasAlt":true,"isDecorative":true,"isMissingAlt":false,"ariaHidden":true,"rolePresentation":false,"renderedWidth":64,"renderedHeight":64,"naturalWidth":64,"naturalHeight":64,"loading":null,"decoding":null,"altVerdict":"DECORATIVE","altReason":"aria-hidden=\"true\"","bytes":344},{"src":"https://www.medicaid.gov/themes/custom/medicaid/images/logo/medicaid_logo_green.svg","alt":"Medicaid.gov-Keeping America Healthy","hasAlt":true,"isDecorative":false,"isMissingAlt":false,"ariaHidden":false,"rolePresentation":false,"renderedWidth":302,"renderedHeight":61,"naturalWidth":300,"naturalHeight":61,"loading":null,"decoding":null,"altVerdict":"GOOD","altReason":"present, no red flags","bytes":2854},{"src":"https://www.medicaid.gov/themes/custom/medicaid/dist/img/usa-icons-bg/search--white.svg","alt":"Search","hasAlt":true,"isDecorative":false,"isMissingAlt":false,"ariaHidden":false,"rolePresentation":false,"renderedWidth":24,"renderedHeight":24,"naturalWidth":24,"naturalHeight":24,"loading":null,"decoding":null,"altVerdict":"GOOD","altReason":"present, no red flags","bytes":224},{"src":"https://www.medicaid.gov/themes/custom/medicaid/dist/img/usa-icons/close.svg","alt":"Close","hasAlt":true,"isDecorative":false,"isMissingAlt":false,"ariaHidden":false,"rolePresentation":false,"renderedWidth":24,"renderedHeight":24,"naturalWidth":24,"naturalHeight":24,"loading":null,"decoding":null,"altVerdict":"GOOD","altReason":"present, no red flags","bytes":128},{"src":"https://www.medicaid.gov/themes/custom/medicaid/dist/img/usa-icons-bg/search--white.svg","alt":"Search","hasAlt":true,"isDecorative":false,"isMissingAlt":false,"ariaHidden":false,"rolePresentation":false,"renderedWidth":24,"renderedHeight":24,"naturalWidth":24,"naturalHeight":24,"loading":null,"decoding":null,"altVerdict":"GOOD","altReason":"present, no red flags","bytes":224},{"src":"https://www.medicaid.gov/themes/custom/medicaid/images/logo/medicaid_logo_green.svg","alt":"Medicaid.gov: Keeping America Healthy","hasAlt":true,"isDecorative":false,"isMissingAlt":false,"ariaHidden":false,"rolePresentation":false,"renderedWidth":228,"renderedHeight":46,"naturalWidth":300,"naturalHeight":61,"loading":null,"decoding":null,"altVerdict":"GOOD","altReason":"present, no red flags","bytes":2854},{"src":"https://www.medicaid.gov/themes/custom/medicaid/dist/img/usa-icons/close.svg","alt":"Close","hasAlt":true,"isDecorative":false,"isMissingAlt":false,"ariaHidden":false,"rolePresentation":false,"renderedWidth":24,"renderedHeight":24,"naturalWidth":24,"naturalHeight":24,"loading":null,"decoding":null,"altVerdict":"GOOD","altReason":"present, no red flags","bytes":128}]},"publicInterest":{"engine":"public-interest","checkedAt":"2026-07-19T07:14:56.149Z","a11yStatement":{"result":"pass","url":"https://www.cms.gov/about-cms/web-policies-important-links/accessibility-nondiscrimination-disabilities-notice","confidence":"medium","checkedAt":"2026-07-19T07:14:53.996Z"},"carbonTxt":{"result":"fail","url":null,"valid":false,"fields":{},"checkedAt":"2026-07-19T07:14:53.998Z"},"greenWebFoundation":{"result":"fail","green":false,"hostedBy":null,"url":"https://api.thegreenwebfoundation.org/greencheck/medicaid.gov","checkedAt":"2026-07-19T07:14:53.999Z"},"sitemaps":{"xml":{"found":true,"url":"https://www.medicaid.gov/sitemap.xml"},"human":{"found":false,"url":null},"checkedAt":"2026-07-19T07:14:54.000Z"}},"thirdParty":{"engine":"third-party","pageUrl":"https://www.medicaid.gov/medicaid/section-1115-demo/demonstration-and-waiver-list?items_per_page=10&page=2&sl=yes&usid=KY","thirdPartyOrigins":9,"scriptOrigins":8,"totalThirdPartyRequests":32,"totalThirdPartyBytes":1202584,"totalThirdPartyScripts":24,"firstPartyRequests":127,"firstPartyBytes":636836,"origins":[{"origin":"qualtrics.com","requests":14,"bytes":849492,"scripts":9,"byType":{"script":9,"xhr":4,"fetch":1},"totalDurationMs":585},{"origin":"googletagmanager.com","requests":1,"bytes":155952,"scripts":1,"byType":{"script":1},"totalDurationMs":3},{"origin":"jsdelivr.net","requests":6,"bytes":49850,"scripts":4,"byType":{"stylesheet":1,"script":4,"xhr":1},"totalDurationMs":434},{"origin":"chartbeat.com","requests":1,"bytes":40167,"scripts":1,"byType":{"script":1},"totalDurationMs":1},{"origin":"cloudflare.com","requests":2,"bytes":31878,"scripts":2,"byType":{"script":2},"totalDurationMs":200},{"origin":"digitalgov.gov","requests":1,"bytes":30230,"scripts":1,"byType":{"script":1},"totalDurationMs":1},{"origin":"tiqcdn.com","requests":5,"bytes":24789,"scripts":5,"byType":{"script":5},"totalDurationMs":12},{"origin":"adoberesources.net","requests":1,"bytes":20183,"scripts":1,"byType":{"script":1},"totalDurationMs":1},{"origin":"chartbeat.net","requests":1,"bytes":43,"scripts":0,"byType":{"image":1},"totalDurationMs":6}]}}