{"pageId":"c9db946071caf360","url":"https://www.cdc.gov/mmwr/preview/mmwrhtml/mm6109a3.htm?s_cid=mm6109a3_w","week":"2026-W30","runId":"2026-07-23T08-28-29-672Z-9eac43","scannedAt":"2026-07-23T09:10:08.207Z","status":200,"depth":4,"sustainability":{"engine":"sustainability","requests":62,"bytes":395158,"byType":{"document":17083,"stylesheet":32006,"script":250992,"image":94522,"fetch":555},"co2g":0.0586,"energyWh":0.1185,"model":"swd-v4 (co2.js)"},"axe":{"engine":"axe-core","version":"4.12.1","violationCount":60,"violations":{"color-contrast":{"count":2,"impact":"serious","help":"Elements must meet minimum color contrast ratio thresholds","helpUrl":"https://dequeuniversity.com/rules/axe/4.12/color-contrast?application=axeAPI","tags":["wcag2aa","wcag143"],"examples":[{"target":"font[color=\"red\"]","html":"<font color=\"red\">Persons using assistive technology might not be able to fully access information in this file. For assistance, please send e-mail to: <a href=\"mailto:mmwrq@cdc.gov\">mmwrq@cdc.gov</a>"},{"target":"font[color=\"#FF0000\"] > b","html":"<b>Please note: </b>"}]},"label":{"count":1,"impact":"critical","help":"Form elements must have labels","helpUrl":"https://dequeuniversity.com/rules/axe/4.12/label?application=axeAPI","tags":["wcag2a","wcag412"],"examples":[{"target":"#searchBox","html":"<input id=\"searchBox\" class=\"searchBox\" name=\"query\" maxlength=\"256\" type=\"text\" style=\"width: 230px;\">"}]},"landmark-one-main":{"count":1,"impact":"moderate","help":"Document should have one main landmark","helpUrl":"https://dequeuniversity.com/rules/axe/4.12/landmark-one-main?application=axeAPI","tags":["best-practice"],"examples":[{"target":"#js","html":"<html xmlns=\"http://www.w3.org/1999/xhtml\" xml:lang=\"en\" lang=\"en\" id=\"js\">"}]},"region":{"count":56,"impact":"moderate","help":"All page content should be contained by landmarks","helpUrl":"https://dequeuniversity.com/rules/axe/4.12/region?application=axeAPI","tags":["best-practice"],"examples":[{"target":"#homeward","html":"<span id=\"homeward\"><a href=\"https://www.cdc.gov/\" title=\"Return to the CDC Home Page\">CDC Home</a></span>"},{"target":"#searchBox","html":"<input id=\"searchBox\" class=\"searchBox\" name=\"query\" maxlength=\"256\" type=\"text\" style=\"width: 230px;\">"},{"target":"#topic-title","html":"<div id=\"topic-title\"><!-- InstanceBeginEditable name=\"topic-title\" -->\n<h2><a href=\"/mmwr/\">Morbidity and Mortality Weekly Report (<i>MMWR</i>)</a></h2>\n<!-- InstanceEndEditable -->\n    </div>"}]}},"incompleteCount":35},"resources":{"engine":"resources","count":3,"byType":{"pdf":3},"resources":[{"url":"https://www.cdc.gov/mmwr/pdf/wk/mm6109.pdf","type":"pdf"},{"url":"http://www.hcup-us.ahrq.gov/reports/statbriefs/sb124.pdf","type":"pdf"},{"url":"http://www.effectivehealthcare.ahrq.gov/ehc/products/115/822/cer-31_cdiff_execsummary_20111220.pdf","type":"pdf"}]},"images":{"engine":"images","count":24,"images":[{"src":"https://www.cdc.gov/TemplatePackage/images/cdcHeaderLogo.gif","alt":"CDC. Centers for Disease Control and Prevention. CDC 24/7: Saving Lives. Protecting People.","hasAlt":true,"isDecorative":false,"isMissingAlt":false,"ariaHidden":false,"rolePresentation":false,"renderedWidth":470,"renderedHeight":47,"naturalWidth":470,"naturalHeight":47,"loading":null,"decoding":null,"altVerdict":"GOOD","altReason":"present, no red flags","bytes":6834},{"src":"https://www.cdc.gov/TemplatePackage/images/icon_pdf.gif","alt":"Adobe PDF file","hasAlt":true,"isDecorative":false,"isMissingAlt":false,"ariaHidden":false,"rolePresentation":false,"renderedWidth":14,"renderedHeight":14,"naturalWidth":16,"naturalHeight":16,"loading":null,"decoding":null,"altVerdict":"GOOD","altReason":"present, no red flags","bytes":6058},{"src":"https://www.cdc.gov/TemplatePackage/images/icon_pdf.gif","alt":"Adobe PDF file","hasAlt":true,"isDecorative":false,"isMissingAlt":false,"ariaHidden":false,"rolePresentation":false,"renderedWidth":16,"renderedHeight":16,"naturalWidth":16,"naturalHeight":16,"loading":null,"decoding":null,"altVerdict":"GOOD","altReason":"present, no red flags","bytes":6058},{"src":"https://www.cdc.gov/TemplatePackage/images/icon_out.png","alt":"External Web Site Icon","hasAlt":true,"isDecorative":false,"isMissingAlt":false,"ariaHidden":false,"rolePresentation":false,"renderedWidth":10,"renderedHeight":10,"naturalWidth":10,"naturalHeight":10,"loading":null,"decoding":null,"altVerdict":"GOOD","altReason":"present, no red flags","bytes":232},{"src":"https://www.cdc.gov/TemplatePackage/images/icon_pdf.gif","alt":"Adobe PDF file","hasAlt":true,"isDecorative":false,"isMissingAlt":false,"ariaHidden":false,"rolePresentation":false,"renderedWidth":16,"renderedHeight":16,"naturalWidth":16,"naturalHeight":16,"loading":null,"decoding":null,"altVerdict":"GOOD","altReason":"present, no red flags","bytes":6058},{"src":"https://www.cdc.gov/TemplatePackage/images/icon_out.png","alt":"External Web Site Icon","hasAlt":true,"isDecorative":false,"isMissingAlt":false,"ariaHidden":false,"rolePresentation":false,"renderedWidth":10,"renderedHeight":10,"naturalWidth":10,"naturalHeight":10,"loading":null,"decoding":null,"altVerdict":"GOOD","altReason":"present, no red flags","bytes":232},{"src":"https://www.cdc.gov/TemplatePackage/images/icon_out.png","alt":"External Web Site Icon","hasAlt":true,"isDecorative":false,"isMissingAlt":false,"ariaHidden":false,"rolePresentation":false,"renderedWidth":10,"renderedHeight":10,"naturalWidth":10,"naturalHeight":10,"loading":null,"decoding":null,"altVerdict":"GOOD","altReason":"present, no red flags","bytes":232},{"src":"https://www.cdc.gov/TemplatePackage/images/icon_out.png","alt":"External Web Site Icon","hasAlt":true,"isDecorative":false,"isMissingAlt":false,"ariaHidden":false,"rolePresentation":false,"renderedWidth":10,"renderedHeight":10,"naturalWidth":10,"naturalHeight":10,"loading":null,"decoding":null,"altVerdict":"GOOD","altReason":"present, no red flags","bytes":232},{"src":"https://www.cdc.gov/TemplatePackage/images/icon_out.png","alt":"External Web Site Icon","hasAlt":true,"isDecorative":false,"isMissingAlt":false,"ariaHidden":false,"rolePresentation":false,"renderedWidth":10,"renderedHeight":10,"naturalWidth":10,"naturalHeight":10,"loading":null,"decoding":null,"altVerdict":"GOOD","altReason":"present, no red flags","bytes":232},{"src":"https://www.cdc.gov/TemplatePackage/images/icon_out.png","alt":"External Web Site Icon","hasAlt":true,"isDecorative":false,"isMissingAlt":false,"ariaHidden":false,"rolePresentation":false,"renderedWidth":10,"renderedHeight":10,"naturalWidth":10,"naturalHeight":10,"loading":null,"decoding":null,"altVerdict":"GOOD","altReason":"present, no red flags","bytes":232},{"src":"https://www.cdc.gov/mmwr/preview/mmwrhtml/figures/m6109a3f1.gif","alt":"The figure shows the percentage of Clostridium difficile infection (CDI) cases (N = 10,342), by inpatient or outpatient status at time of stool collection and type/location of exposures, in the United States during 2010, based on data from the Emerging Infections Program. The population under surveillance included persons in the catchment areas of 111 acute-care hospitals and 310 nursing homes. A total of 10,342 CDIs were identified. CDIs were classified by inpatient or outpatient status at time of stool collection and type/location of exposures. Overall, 94% of all CDIs were related to various antecedent and concurrent health-care exposures; of these, 75% had their onset outside of hospitals. In addition, some cases occurred in patients who were exposed to multiple settings. For example, 20% of hospital-onset CDIs occurred in recent (i.e., <12 weeks) residents of a nursing home, and 67% of nursing home-onset CDI cases occurred in patients recently discharged from an acute-care hospital.","hasAlt":true,"isDecorative":false,"isMissingAlt":false,"ariaHidden":false,"rolePresentation":false,"renderedWidth":511,"renderedHeight":351,"naturalWidth":511,"naturalHeight":351,"loading":null,"decoding":null,"altVerdict":"TOO_LONG","altReason":"alt text is 1002 characters — consider a caption or description","bytes":13722},{"src":"https://www.cdc.gov/mmwr/preview/mmwrhtml/figures/m6109a3f2.gif","alt":"The figure shows the percentage of laboratory-identified Clostridium difficile infections (LabID-CDIs) (N = 42,157), by hospitalization status at time of stool collection and type/location of exposure in the United States, during 2010, based on data from the National Healthcare Safety Network. Surveillance was conducted over approximately 27.6 million patient days. A total of 42,157 incident LabID-CDIs were reported. Overall, 52% of LabID-CDIs events were already present on admission to hospitals. The pooled rate of hospital onset CDI was 7.4 per 10,000 patient-days, with a median hospital rate of 5.4 per 10,000 and an interquartile range of 6.2.","hasAlt":true,"isDecorative":false,"isMissingAlt":false,"ariaHidden":false,"rolePresentation":false,"renderedWidth":497,"renderedHeight":386,"naturalWidth":497,"naturalHeight":386,"loading":null,"decoding":null,"altVerdict":"TOO_LONG","altReason":"alt text is 654 characters — consider a caption or description","bytes":11042},{"src":"https://www.cdc.gov/TemplatePackage/images/icon_pdf.gif","alt":"Adobe PDF file","hasAlt":true,"isDecorative":false,"isMissingAlt":false,"ariaHidden":false,"rolePresentation":false,"renderedWidth":16,"renderedHeight":16,"naturalWidth":16,"naturalHeight":16,"loading":null,"decoding":null,"altVerdict":"GOOD","altReason":"present, no red flags","bytes":6058},{"src":"https://www.cdc.gov/TemplatePackage/images/icon_word.gif","alt":"Microsoft Word file","hasAlt":true,"isDecorative":false,"isMissingAlt":false,"ariaHidden":false,"rolePresentation":false,"renderedWidth":16,"renderedHeight":16,"naturalWidth":16,"naturalHeight":16,"loading":null,"decoding":null,"altVerdict":"GOOD","altReason":"present, no red flags","bytes":1087},{"src":"https://www.cdc.gov/TemplatePackage/images/icon_excel.gif","alt":"Microsoft Excel file","hasAlt":true,"isDecorative":false,"isMissingAlt":false,"ariaHidden":false,"rolePresentation":false,"renderedWidth":16,"renderedHeight":16,"naturalWidth":16,"naturalHeight":16,"loading":null,"decoding":null,"altVerdict":"GOOD","altReason":"present, no red flags","bytes":644},{"src":"https://www.cdc.gov/TemplatePackage/images/icon_ppt.gif","alt":"Microsoft PowerPoint file","hasAlt":true,"isDecorative":false,"isMissingAlt":false,"ariaHidden":false,"rolePresentation":false,"renderedWidth":16,"renderedHeight":16,"naturalWidth":16,"naturalHeight":16,"loading":null,"decoding":null,"altVerdict":"GOOD","altReason":"present, no red flags","bytes":676},{"src":"https://www.cdc.gov/TemplatePackage/images/icon_wmv.gif","alt":"Audio/Video file","hasAlt":true,"isDecorative":false,"isMissingAlt":false,"ariaHidden":false,"rolePresentation":false,"renderedWidth":16,"renderedHeight":16,"naturalWidth":16,"naturalHeight":16,"loading":null,"decoding":null,"altVerdict":"GOOD","altReason":"present, no red flags","bytes":622},{"src":"https://www.cdc.gov/TemplatePackage/images/icon_zip.gif","alt":"Zip Archive file","hasAlt":true,"isDecorative":false,"isMissingAlt":false,"ariaHidden":false,"rolePresentation":false,"renderedWidth":16,"renderedHeight":16,"naturalWidth":16,"naturalHeight":16,"loading":null,"decoding":null,"altVerdict":"GOOD","altReason":"present, no red flags","bytes":237},{"src":"https://www.cdc.gov/TemplatePackage/images/icon_real.gif","alt":"RealPlayer file","hasAlt":true,"isDecorative":false,"isMissingAlt":false,"ariaHidden":false,"rolePresentation":false,"renderedWidth":16,"renderedHeight":16,"naturalWidth":16,"naturalHeight":16,"loading":null,"decoding":null,"altVerdict":"GOOD","altReason":"present, no red flags","bytes":1016},{"src":"https://www.cdc.gov/TemplatePackage/images/icon_qt.gif","alt":"Apple Quicktime file","hasAlt":true,"isDecorative":false,"isMissingAlt":false,"ariaHidden":false,"rolePresentation":false,"renderedWidth":16,"renderedHeight":16,"naturalWidth":16,"naturalHeight":16,"loading":null,"decoding":null,"altVerdict":"GOOD","altReason":"present, no red flags","bytes":1014},{"src":"https://www.cdc.gov/TemplatePackage/images/btn_dblArrows.gif","alt":"double arrows.","hasAlt":true,"isDecorative":false,"isMissingAlt":false,"ariaHidden":false,"rolePresentation":false,"renderedWidth":7,"renderedHeight":6,"naturalWidth":7,"naturalHeight":6,"loading":null,"decoding":null,"altVerdict":"GOOD","altReason":"present, no red flags","bytes":1298},{"src":"https://www.cdc.gov/TemplatePackage/images/icon_pdf.gif","alt":"Adobe PDF file","hasAlt":true,"isDecorative":false,"isMissingAlt":false,"ariaHidden":false,"rolePresentation":false,"renderedWidth":16,"renderedHeight":16,"naturalWidth":16,"naturalHeight":16,"loading":null,"decoding":null,"altVerdict":"GOOD","altReason":"present, no red flags","bytes":6058},{"src":"https://www.cdc.gov/TemplatePackage/images/logo_usagov.gif","alt":"USA.gov: The U.S. Government's Official Web Portal","hasAlt":true,"isDecorative":false,"isMissingAlt":false,"ariaHidden":false,"rolePresentation":false,"renderedWidth":188,"renderedHeight":55,"naturalWidth":188,"naturalHeight":55,"loading":null,"decoding":null,"altVerdict":"GOOD","altReason":"present, no red flags","bytes":1933},{"src":"https://www.cdc.gov/TemplatePackage/images/logo_dhhs.gif","alt":"Department of Health and Human Services","hasAlt":true,"isDecorative":false,"isMissingAlt":false,"ariaHidden":false,"rolePresentation":false,"renderedWidth":61,"renderedHeight":55,"naturalWidth":61,"naturalHeight":55,"loading":null,"decoding":null,"altVerdict":"GOOD","altReason":"present, no red flags","bytes":1142}]},"standards":{"engine":"standards","checks":[{"id":"schema-gov","label":"schema.org GovernmentOrganization markup","pass":false,"detail":""},{"id":"canonical","label":"Canonical URL declared","pass":false,"detail":""},{"id":"hreflang","label":"hreflang alternates declared","pass":false,"detail":""},{"id":"title","label":"Page has a <title>","pass":true,"detail":""},{"id":"description","label":"Meta description present","pass":false,"detail":""},{"id":"charset","label":"Character encoding declared","pass":false,"detail":""},{"id":"lang","label":"Document language (lang) set","pass":true,"detail":"en"},{"id":"viewport","label":"Responsive viewport (zoom not disabled)","pass":false,"detail":""},{"id":"open-graph","label":"Open Graph tags (0/6)","pass":false,"detail":""},{"id":"twitter-card","label":"Twitter card metadata","pass":false,"detail":""},{"id":"open-social","label":"Open social presence (Mastodon/Bluesky) linked","pass":false,"detail":""}],"passed":2,"total":11,"social":[],"og":{"title":null,"description":null,"url":null,"image":null,"siteName":null,"type":null},"resilience":{"checks":[{"id":"pwa-https","label":"HTTPS (required for service workers)","status":"pass","evidence":"","exampleUrl":"https://www.cdc.gov/mmwr/preview/mmwrhtml/mm6109a3.htm?s_cid=mm6109a3_w","why":"HTTPS is required for service workers and most install prompts."},{"id":"pwa-manifest","label":"Web app manifest declared","status":"fail","evidence":"","exampleUrl":"https://www.cdc.gov/mmwr/preview/mmwrhtml/mm6109a3.htm?s_cid=mm6109a3_w","why":"A web app manifest is required for installability and controls how the app appears when launched."},{"id":"pwa-service-worker","label":"Service worker registered","status":"fail","evidence":"","exampleUrl":"https://www.cdc.gov/mmwr/preview/mmwrhtml/mm6109a3.htm?s_cid=mm6109a3_w","why":"A service worker is what makes offline access, caching, and background sync possible."},{"id":"pwa-theme-color","label":"Theme color declared","status":"fail","evidence":"","exampleUrl":"https://www.cdc.gov/mmwr/preview/mmwrhtml/mm6109a3.htm?s_cid=mm6109a3_w","why":"Theme color controls the browser chrome/status-bar color when the site is installed or bookmarked."},{"id":"pwa-apple-touch-icon","label":"Apple touch icon (iOS/bookmark icon)","status":"fail","evidence":"","exampleUrl":"https://www.cdc.gov/mmwr/preview/mmwrhtml/mm6109a3.htm?s_cid=mm6109a3_w","why":"iOS uses this icon for home-screen bookmarks and \"Add to Home Screen\" — without it the icon falls back to a screenshot."},{"id":"manifest-parsed","label":"Manifest fetched and parsed successfully","status":"n/a","evidence":"No manifest declared","exampleUrl":"https://www.cdc.gov/mmwr/preview/mmwrhtml/mm6109a3.htm?s_cid=mm6109a3_w","why":"A manifest that fails to parse cannot drive installability or launch behavior even if the link is present."},{"id":"manifest-maskable-icon","label":"Manifest declares a maskable icon","status":"n/a","evidence":"No manifest declared","exampleUrl":"https://www.cdc.gov/mmwr/preview/mmwrhtml/mm6109a3.htm?s_cid=mm6109a3_w","why":"A maskable icon lets the OS safely crop/mask the app icon on different device shapes without clipping content."},{"id":"sw-active","label":"Service worker is active (not just registered)","status":"fail","evidence":"","exampleUrl":"https://www.cdc.gov/mmwr/preview/mmwrhtml/mm6109a3.htm?s_cid=mm6109a3_w","why":"An active service worker (not just registered) is what actually intercepts requests and serves cached content."},{"id":"sw-controlling","label":"Service worker controls this page load","status":"fail","evidence":"","exampleUrl":"https://www.cdc.gov/mmwr/preview/mmwrhtml/mm6109a3.htm?s_cid=mm6109a3_w","why":"A controlling service worker means THIS page load is being served/intercepted, not just a future one."},{"id":"installable","label":"Meets basic installability criteria","status":"fail","evidence":"no readable web app manifest; no service worker registered","exampleUrl":"https://www.cdc.gov/mmwr/preview/mmwrhtml/mm6109a3.htm?s_cid=mm6109a3_w","why":"Determines whether the browser can realistically offer \"Add to Home Screen\" / install, based on manifest + service worker + HTTPS together."}],"manifest":null,"serviceWorker":{"registered":false,"active":false,"installing":false,"waiting":false,"controllingThisPage":false}}}}