{"pageId":"a1880d5e4270cda6","url":"https://data.medicaid.gov/dataset/289182e5-44c8-4fcc-96c4-4af69be9863f?page=3","week":"2026-W28","runId":"2026-07-07T11-20-49-171Z-5fb152","scannedAt":"2026-07-07T11:33:11.959Z","status":200,"depth":2,"axe":{"engine":"axe-core","version":"4.12.1","violationCount":0,"violations":{},"incompleteCount":32},"plainLanguage":{"engine":"plain-language","scored":false,"wordCount":2177,"misspelledCount":188,"misspelled":["subpopulation","Geocoding","visitUpdated","TableOverviewData","DictionaryAPI","rowsFilter","DatasetFilter","DatasetAdd","NameConditionValueColumn","NameYearConditionIsValue","filterResetApply","filtersManage","ColumnsManage","columnsActivate","allDisplay","columnReorderyeargeographysubpopulation","topicsubpopulationcategorycount","enrolleesdenominator","enrolleespercentage","enrolleesdata","draggable","SaveCancelReset","ColumnsDisplay","SettingsFull","ScreenDataset"],"sentenceCount":47,"fleschReadingEase":null,"fleschKincaidGrade":null,"avgSentenceLength":null,"longSentences":0,"passiveVoiceRatio":null,"unexplainedAcronyms":["MSIS","DS","CMS","ZIP","ISO","CSV"],"unexplainedAcronymCount":6},"resources":{"engine":"resources","count":1,"byType":{"spreadsheet":1},"resources":[{"url":"https://download.medicaid.gov/data/well-child-visits-2020-2022-01162025.csv","type":"spreadsheet"}]},"images":{"engine":"images","count":1,"images":[{"src":"https://data.medicaid.gov/frontend/build/static/media/dataMedicaid-logo.png","alt":"data.medicaid.gov Logo","hasAlt":true,"isDecorative":false,"isMissingAlt":false,"ariaHidden":false,"rolePresentation":false,"renderedWidth":250,"renderedHeight":32,"naturalWidth":459,"naturalHeight":58,"loading":null,"decoding":null,"altVerdict":"GOOD","altReason":"present, no red flags","bytes":7892}]},"security":{"engine":"security","checks":[{"id":"https","label":"Served over HTTPS","pass":true,"detail":"https:"},{"id":"hsts","label":"HTTP Strict Transport Security (HSTS)","pass":true,"detail":""},{"id":"csp","label":"Content Security Policy (CSP)","pass":false,"detail":""},{"id":"x-content-type-options","label":"X-Content-Type-Options: nosniff","pass":true,"detail":""},{"id":"clickjacking","label":"Clickjacking protection (X-Frame-Options or CSP frame-ancestors)","pass":true,"detail":""},{"id":"gov-tld","label":"Sponsored government TLD (.gov/.mil/.edu)","pass":true,"detail":"gov"},{"id":"security-txt","label":"Published security.txt","pass":false,"detail":""},{"id":"www-resolution","label":"Resolves with and without www","pass":false,"detail":"www.data.medicaid.gov"}],"passed":5,"total":8}}