{"pageId":"ca8e7a58ff5a76f9","url":"https://www.cms.gov/priorities/key-initiatives/burden-reduction/customer-engagement","week":"2026-W24","runId":"2026-06-13T21-25-44-660Z-f56476","scannedAt":"2026-06-13T21:29:57.162Z","status":200,"depth":1,"axe":{"engine":"axe-core","version":"4.12.1","violationCount":0,"violations":{},"incompleteCount":8},"plainLanguage":{"engine":"plain-language","scored":false,"wordCount":386,"sentenceCount":9,"fleschReadingEase":null,"fleschKincaidGrade":null,"avgSentenceLength":null,"longSentences":0,"passiveVoiceRatio":null,"unexplainedAcronyms":["OHEI","CMS","SUD","PDF","PM"],"unexplainedAcronymCount":5},"deprecatedHtml":{"engine":"deprecated-html","findingCount":0,"findings":{}},"sustainability":{"engine":"sustainability","requests":47,"bytes":2057816,"byType":{"document":32999,"image":294163,"script":776331,"stylesheet":380404,"font":570692,"fetch":387,"xhr":2840},"co2g":0.305,"model":"swd-v4 (co2.js)"}}