{
 "runId": "2026-07-20T04-27-19-489Z-97f372",
 "week": "2026-W30",
 "domain": "www.cms.gov",
 "startedAt": "2026-07-20T04:27:20.332Z",
 "scanned": [
  "178558bfd3e7a005",
  "bc8eb5a34965a0d4",
  "78c4a7a2511f0970",
  "e19747109079521c",
  "c8442c413392bb39",
  "64584d458783c037",
  "bbff4b01d5b0ef0a",
  "59759b1745934239",
  "d5e253d7fa5a202f",
  "22f46a7501dde9cb",
  "7adce889b15c042a",
  "01def5f9fb37fbf2",
  "c828c17dc163c99c",
  "96632866a6e91dea",
  "6c4974138e2fb56f",
  "336c78e9ce51553b",
  "e499742783b26bf4",
  "ba67a8437ce1a8cd",
  "4095f891eb1bfd79",
  "9f04fd3e42cbb9ad",
  "01958cd9c1f15d00",
  "3935ff3cbf6ebf9c",
  "b4d136fac72cab2d",
  "488eeee75a5c7973",
  "6f4f074125497aa9",
  "493fd56fd46ccf99",
  "4cdd47fbe282e11d",
  "2bc988bfba1315a7",
  "4b52f4aeffed05ee",
  "dd7a8b5ae4c9acf4",
  "0b4fd2dcaf92c3f6",
  "c6cc154549cf2834",
  "c186305b1d9e7cce",
  "429f32577fa2bee2",
  "2d28888b80cc5d54",
  "d3a169a04e48ff15",
  "f33b33f7385502a9",
  "1ddc968fa9cc38f6",
  "6efd3616c15d7319",
  "c8b5ecd22cc67b87",
  "1adaf1d76a506bd6",
  "282a70662d4c1e04",
  "4d373a57275ee664",
  "cf0528b2387f2353",
  "90fd7a2eba0e9689",
  "c24e38e0b3c6c0a4",
  "9c21c0cb6bf50458",
  "adaa0e89c64aec1a",
  "28ebc13daf6aafb1",
  "8cab5717a90f47b9",
  "bda5c07b91aff9e5",
  "980be4ccbf4d8733",
  "c8642dcccdedf4fe",
  "45552690261250f5",
  "61bc6a117b7e5061",
  "2d35a3f21b8ce7a4",
  "ca7866e4ff197dee",
  "2b0e28ea83783d49",
  "c7acfa15231f94cf",
  "2c7f1c4e4c7d9160",
  "efc1bb8faf19a6b0",
  "c361d0da2c150881",
  "08fd6330b92062d3",
  "8b37c62193d1b786",
  "ca6c66abf68cb111",
  "ee5bf93e6567f410",
  "e43b6840418e1041",
  "241f2ede6454dc82",
  "8ffba9c739ea094e",
  "29b557e04c2d4d09",
  "877344d350c90bbb",
  "227c18362bba8849",
  "b3d4d4ff238eaaac",
  "1395520c4b1b38ad",
  "1899fc544663245c",
  "24bc1a6aad7a173b",
  "20db693dfb81e77d",
  "9170968f7aa11e8d",
  "9c159b891f9f3cda",
  "0bca4d3c0c13a693",
  "d5a981365b7ccb41",
  "34ca18c1558535de",
  "dbb36618e6e23a2f",
  "c04fd56ed2453524",
  "b29a7e9b2f8da80e",
  "61d15e1899b35297",
  "1580c7689a8d3191",
  "2a03e4d8fca42a7f",
  "485e9d3577ddc39d",
  "a4c5dd0be04e1661",
  "be8ac59d012b5256",
  "51797b14e5aba57c",
  "860ef71a247174a9",
  "15e8bfa10af2fddf",
  "1bc535efb1840e56",
  "2943a8d0ba494ed9",
  "779bbef1bedd26db",
  "cf67d90b2b797c2c",
  "d881122ee3cdb4ba",
  "818056910151762c",
  "3b1693ad7630a390",
  "ff5f29ecd9d742c2",
  "87f39800f946b46f",
  "19d7e79f8885b04b",
  "c4d4ac50b7bb8378",
  "fb7bc58bbf7c655c",
  "c6df2202f179495a",
  "b437247dc4715180",
  "e15bb4db6a93c079",
  "ca97cba14d634f19",
  "0336187dc0b25bd0",
  "8d0454d88c7f3864",
  "2654449de9dddb5e",
  "5d4e052b53a70dd6",
  "c66e5f1dd988170c",
  "8ed701029e9eb69c",
  "0c0b55abbf67f60e",
  "d8096acb2eb7d7e1",
  "40400f13556a8c01",
  "d269ecfb2a7a5645",
  "f220b25cdaa89c46",
  "d3a8c1137b5f73dd",
  "db35eacc475ff1f9",
  "382c623c7a125215",
  "14faff54a285dab3",
  "814e539287744399",
  "c2e1b4b1e003fe1c",
  "e153a0b800772034",
  "c1731d6e84578532",
  "37382a33f95f3b1a",
  "9762682353efce94",
  "ca8eaaacaa0be444",
  "00c7dbb1bba5b7ed",
  "6b9e3527c2201ebf",
  "16a2a69b968827be",
  "c06d88409a563dfc",
  "8af648d1b89ba16e",
  "a710f0d3361deb95",
  "f5c14d581f778af0",
  "c80f3e50ea39a4f5",
  "ef9baeb9df407420",
  "cd586d90b3e1eca7",
  "b366b8d49f38ed1c",
  "6387ebf204b4812c",
  "4ff013a8cf7437cd",
  "d5fc73f788ef370c",
  "855cb43c9183ab16",
  "4658d157df0622d7"
 ],
 "errors": [],
 "sampling": {
  "axe": 100,
  "alfa": 25,
  "plain-language": 50,
  "link-check": 100,
  "lighthouse": 10,
  "deprecated-html": 10,
  "resources": 100,
  "images": 100,
  "standards": 50,
  "security": 10,
  "public-interest": 10,
  "offline-resilience": 0,
  "sustainability": 10,
  "tech": 10,
  "third-party": 25
 },
 "linkCheck": {
  "total": 4699,
  "checked": 500,
  "brokenCount": 3,
  "broken": [
   {
    "url": "https://www.cms.gov/medicare-coverage-database/search.aspx",
    "status": 503,
    "reason": "HTTP 503",
    "foundOn": [
     "https://www.cms.gov/about-cms/who-we-are/leadership/office-healthcare-experience-interoperability",
     "https://www.cms.gov/marketplace/resources/data/healthcaregov-plan-finder-data",
     "https://www.cms.gov/about-cms/who-we-are/leadership/office-legislation",
     "https://www.cms.gov/medicare/appeals-grievances/fee-for-service",
     "https://www.cms.gov/medicare/coding-billing/place-of-service-codes",
     "https://www.cms.gov/medicare/coding-billing/national-correct-coding-initiative-ncci-edits/medicare-ncci-medically-unlikely-edits-mues",
     "https://www.cms.gov/cms-l564-solicitud-de-informacion-sobre-el-empleo",
     "https://www.cms.gov/nosurprises/help-resolve-payment-disputes/tips-for-disputing-parties",
     "https://www.cms.gov/medicare/coding-billing/national-correct-coding-initiative-ncci-edits/medicare-ncci-procedure-procedure-ptp-edits",
     "https://www.cms.gov/medicare/payment/medicare-advantage-rates-statistics/announcements-and-documents",
     "https://www.cms.gov/data-research/computer-data-systems/minimum-data-sets-3.0-public-reports",
     "https://www.cms.gov/data-research/research/consumer-assessment-healthcare-providers-systems/cahps-hospice",
     "https://www.cms.gov/medicare/coding-billing/provider-customer-service-program",
     "https://www.cms.gov/medicare/medicaid-coordination/states/medicaid-integrity-program",
     "https://www.cms.gov/about-cms/who-we-are/leadership/federal-coordinated-health-care-office",
     "https://www.cms.gov/data-research/monitoring-programs/medicare-fee-service-compliance-programs/prior-authorization-and-pre-claim-review-initiatives",
     "https://www.cms.gov/about-cms/contact/speech-meeting-requests",
     "https://www.cms.gov/medicare/physician-fee-schedule/search/documentation",
     "https://www.cms.gov/nosurprises/policies-and-resources/overview-of-rules-fact-sheets",
     "https://www.cms.gov/priorities/innovation-center/value-based-care-spotlight/patient-provider-voices/whole-person-care-stories/improving-health-access-care-rural-areas-one-pennsylvania-couples-story",
     "https://www.cms.gov/medicare/forms-notices/cms-forms",
     "https://www.cms.gov/about-cms/who-we-are/leadership/office-enterprise-data-analytics",
     "https://www.cms.gov/about-cms/who-we-are/leadership/center-consumer-information-insurance-oversight",
     "https://www.cms.gov/medicare/coding-billing/icd-10-codes",
     "https://www.cms.gov/about-cms/contact/database",
     "https://www.cms.gov/about-cms/what-we-do/nursing-homes/patients-caregivers/finding-nursing-home",
     "https://www.cms.gov/training-education/partner-outreach-resources/american-indian-alaska-native/ltss-ta-center/information/state-resources-map",
     "https://www.cms.gov/about-cms/information-systems/privacy/privacy-act-1974-and-privacy-act-requests",
     "https://www.cms.gov/about-cms/information-systems/hpms/help-desk-information",
     "https://www.cms.gov/nosurprises/policies-and-resources",
     "https://www.cms.gov/data-research/cms-information-technology/tlc",
     "https://www.cms.gov/data-research",
     "https://www.cms.gov/data-research/cms-information-technology/section-508-cms/contractors-developers",
     "https://www.cms.gov/training-education/find-provider-type/employers-unions/publications-share-employees",
     "https://www.cms.gov/outreach-and-education/reach-out/find-tools-to-help-you-help-others/open-enrollment-outreach-and-media-materials",
     "https://www.cms.gov/medicare/coding-billing/place-of-service-codes/code-sets",
     "https://www.cms.gov/medicare/medicaid-coordination/center-program-integrity/reporting-fraud",
     "https://www.cms.gov/medicaid-chip/medicare-coordination/integrity-institute/contact",
     "https://www.cms.gov/digital-service/findsupportgov",
     "https://www.cms.gov/about-cms/web-policies-important-links/accessibility-nondiscrimination-disabilities-notice",
     "https://www.cms.gov/training-education/find-provider-type/employers-unions/top-five-medicare-enrollment",
     "https://www.cms.gov/medicare/coding-billing/therapy-services",
     "https://www.cms.gov/about-cms/leadership/organization",
     "https://www.cms.gov/outreach-and-education/american-indian-alaska-native/aian/outreach-and-education/whats-covered",
     "https://www.cms.gov/medicare/physician-fee-schedule/search",
     "https://www.cms.gov/data-research/monitoring-programs/improper-payment-measurement-programs/medicare-part-c-ipm/error-rate-findings-results",
     "https://www.cms.gov/training-education/find-provider-type/employers-unions",
     "https://www.cms.gov/training-education/open-door-forums/long-term-services-supports",
     "https://www.cms.gov/about-cms/who-we-are/leadership/center-clinical-standards-quality",
     "https://www.cms.gov/privacy/third-party-privacy-policies"
    ]
   },
   {
    "url": "https://www.agentbrokerfaq.cms.gov/s/",
    "status": 0,
    "reason": "UNABLE_TO_VERIFY_LEAF_SIGNATURE",
    "foundOn": [
     "https://www.cms.gov/about-cms/who-we-are/leadership/office-healthcare-experience-interoperability",
     "https://www.cms.gov/marketplace/resources/data/healthcaregov-plan-finder-data",
     "https://www.cms.gov/about-cms/who-we-are/leadership/office-legislation",
     "https://www.cms.gov/medicare/appeals-grievances/fee-for-service",
     "https://www.cms.gov/medicare/coding-billing/place-of-service-codes",
     "https://www.cms.gov/medicare/coding-billing/national-correct-coding-initiative-ncci-edits/medicare-ncci-medically-unlikely-edits-mues",
     "https://www.cms.gov/cms-l564-solicitud-de-informacion-sobre-el-empleo",
     "https://www.cms.gov/nosurprises/help-resolve-payment-disputes/tips-for-disputing-parties",
     "https://www.cms.gov/medicare/coding-billing/national-correct-coding-initiative-ncci-edits/medicare-ncci-procedure-procedure-ptp-edits",
     "https://www.cms.gov/medicare/payment/medicare-advantage-rates-statistics/announcements-and-documents",
     "https://www.cms.gov/data-research/computer-data-systems/minimum-data-sets-3.0-public-reports",
     "https://www.cms.gov/data-research/research/consumer-assessment-healthcare-providers-systems/cahps-hospice",
     "https://www.cms.gov/medicare/coding-billing/provider-customer-service-program",
     "https://www.cms.gov/medicare/medicaid-coordination/states/medicaid-integrity-program",
     "https://www.cms.gov/about-cms/who-we-are/leadership/federal-coordinated-health-care-office",
     "https://www.cms.gov/data-research/monitoring-programs/medicare-fee-service-compliance-programs/prior-authorization-and-pre-claim-review-initiatives",
     "https://www.cms.gov/about-cms/contact/speech-meeting-requests",
     "https://www.cms.gov/medicare/physician-fee-schedule/search/documentation",
     "https://www.cms.gov/nosurprises/policies-and-resources/overview-of-rules-fact-sheets",
     "https://www.cms.gov/priorities/innovation-center/value-based-care-spotlight/patient-provider-voices/whole-person-care-stories/improving-health-access-care-rural-areas-one-pennsylvania-couples-story",
     "https://www.cms.gov/medicare/forms-notices/cms-forms",
     "https://www.cms.gov/about-cms/who-we-are/leadership/office-enterprise-data-analytics",
     "https://www.cms.gov/about-cms/who-we-are/leadership/center-consumer-information-insurance-oversight",
     "https://www.cms.gov/medicare/coding-billing/icd-10-codes",
     "https://www.cms.gov/about-cms/contact/database",
     "https://www.cms.gov/about-cms/what-we-do/nursing-homes/patients-caregivers/finding-nursing-home",
     "https://www.cms.gov/training-education/partner-outreach-resources/american-indian-alaska-native/ltss-ta-center/information/state-resources-map",
     "https://www.cms.gov/about-cms/information-systems/privacy/privacy-act-1974-and-privacy-act-requests",
     "https://www.cms.gov/about-cms/information-systems/hpms/help-desk-information",
     "https://www.cms.gov/nosurprises/policies-and-resources",
     "https://www.cms.gov/data-research/cms-information-technology/tlc",
     "https://www.cms.gov/data-research",
     "https://www.cms.gov/data-research/cms-information-technology/section-508-cms/contractors-developers",
     "https://www.cms.gov/training-education/find-provider-type/employers-unions/publications-share-employees",
     "https://www.cms.gov/outreach-and-education/reach-out/find-tools-to-help-you-help-others/open-enrollment-outreach-and-media-materials",
     "https://www.cms.gov/medicare/coding-billing/place-of-service-codes/code-sets",
     "https://www.cms.gov/medicare/medicaid-coordination/center-program-integrity/reporting-fraud",
     "https://www.cms.gov/medicaid-chip/medicare-coordination/integrity-institute/contact",
     "https://www.cms.gov/digital-service/findsupportgov",
     "https://www.cms.gov/about-cms/web-policies-important-links/accessibility-nondiscrimination-disabilities-notice",
     "https://www.cms.gov/training-education/find-provider-type/employers-unions/top-five-medicare-enrollment",
     "https://www.cms.gov/medicare/coding-billing/therapy-services",
     "https://www.cms.gov/about-cms/leadership/organization",
     "https://www.cms.gov/outreach-and-education/american-indian-alaska-native/aian/outreach-and-education/whats-covered",
     "https://www.cms.gov/medicare/physician-fee-schedule/search",
     "https://www.cms.gov/data-research/monitoring-programs/improper-payment-measurement-programs/medicare-part-c-ipm/error-rate-findings-results",
     "https://www.cms.gov/training-education/find-provider-type/employers-unions",
     "https://www.cms.gov/training-education/open-door-forums/long-term-services-supports",
     "https://www.cms.gov/about-cms/who-we-are/leadership/center-clinical-standards-quality",
     "https://www.cms.gov/privacy/third-party-privacy-policies"
    ]
   },
   {
    "url": "https://www.cms.gov/node/1617276",
    "status": 404,
    "reason": "HTTP 404",
    "foundOn": [
     "https://www.cms.gov/medicare/coding-billing/national-correct-coding-initiative-ncci-edits/medicare-ncci-medically-unlikely-edits-mues",
     "https://www.cms.gov/medicare/coding-billing/national-correct-coding-initiative-ncci-edits/medicare-ncci-procedure-procedure-ptp-edits"
    ]
   }
  ]
 },
 "enginesRun": {
  "axe": 136,
  "plain-language": 70,
  "resources": 136,
  "images": 136,
  "standards": 78,
  "security": 14,
  "link-check": 136,
  "public-interest": 14,
  "alfa": 38,
  "tech": 17,
  "sustainability": 19,
  "lighthouse": 24,
  "third-party": 34,
  "deprecated-html": 11
 },
 "tally": {
  "ok": 136,
  "blocked": 1,
  "timeout": 0,
  "robots_skipped": 2,
  "url_filtered": 0,
  "non_html": 11,
  "error": 0
 },
 "finishedAt": "2026-07-20T04:46:19.883Z"
}