{"pageId":"f6f5f5173fa79431","url":"https://www.nih.gov/news-events/news-releases/scientists-discover-urinary-biomarker-may-help-track-als","week":"2026-W29","runId":"2026-07-14T09-37-03-360Z-395a91","scannedAt":"2026-07-14T09:47:07.497Z","status":404,"depth":7,"sustainability":{"engine":"sustainability","requests":91,"bytes":2068643,"byType":{"stylesheet":957642,"image":39956,"script":866531,"font":83100,"document":45985,"other":72951,"xhr":2478},"co2g":0.3066,"energyWh":0.6206,"model":"swd-v4 (co2.js)"}}