{"pageId":"7909fbb2b4d04fef","url":"https://www.cms.gov/data-research/statistics-trends-and-reports/cms-statistics-reference-booklet/2015-edition","week":"2026-W25","runId":"2026-06-15T09-32-59-679Z-808065","scannedAt":"2026-06-15T09:46:28.434Z","status":200,"depth":1,"axe":{"engine":"axe-core","version":"4.12.1","violationCount":1,"violations":{"heading-order":{"count":1,"impact":"moderate","help":"Heading levels should only increase by one","helpUrl":"https://dequeuniversity.com/rules/axe/4.12/heading-order?application=axeAPI","tags":["best-practice"],"examples":[{"target":".rxbodyfield > h3","html":"<h3><span><strong>Table Listings:</strong></span></h3>"}]}},"incompleteCount":9},"deprecatedHtml":{"engine":"deprecated-html","findingCount":0,"findings":{}},"resources":{"engine":"resources","count":3,"byType":{"pdf":2,"archive":1},"resources":[{"url":"https://www.cms.gov/files/document/agent/broker-help-desks.pdf","type":"pdf"},{"url":"https://www.cms.gov/research-statistics-data-and-systems/statistics-trends-and-reports/cms-statistics-reference-booklet/downloads/2015cmsstatistics.pdf","type":"pdf"},{"url":"https://www.cms.gov/research-statistics-data-and-systems/statistics-trends-and-reports/cms-statistics-reference-booklet/downloads/2015cmsstatsexcel.zip","type":"archive"}]},"sustainability":{"engine":"sustainability","requests":40,"bytes":1231314,"byType":{"document":31405,"stylesheet":78170,"script":581805,"image":4837,"font":526184,"fetch":387,"xhr":8526},"co2g":0.1825,"energyWh":0.3694,"model":"swd-v4 (co2.js)"}}