{"pageId":"dba7de0641209598","url":"https://medicare.gov/providers-services/original-medicare/skilled-nursing/assessments-care-plans","week":"2026-W30","runId":"2026-07-20T04-27-02-871Z-78a7a0","scannedAt":"2026-07-20T04:47:57.722Z","status":200,"depth":4,"axe":{"engine":"axe-core","version":"4.12.1","violationCount":0,"violations":{},"incompleteCount":0},"alfa":{"engine":"alfa","version":"0.117.0","failedCount":46,"failed":{"sia-r73":{"count":5,"ruleUrl":"https://alfa.siteimprove.com/rules/sia-r73","examples":[{"target":"<p>"},{"target":"<p>"},{"target":"<p>"}]},"sia-r17":{"count":1,"ruleUrl":"https://alfa.siteimprove.com/rules/sia-r17","examples":[{"target":"<div class=\"search-block__content\" aria-hidden=\"true\" id=\"search_form_block-content\">"}]},"sia-r111":{"count":40,"ruleUrl":"https://alfa.siteimprove.com/rules/sia-r111","examples":[{"target":"<a href=\"/\" data-listener-attached=\"true\">"},{"target":"<a href=\"/providers-services\" data-listener-attached=\"true\">"},{"target":"<a href=\"/providers-services/original-medicare\" data-listener-attached=\"true\">"}]}},"cantTellCount":4,"passedRules":37},"resources":{"engine":"resources","count":4,"byType":{"iframe":4},"resources":[{"url":"https://apps.use2.us-gov-pure.cloud/messenger/thirdparty-plugins.html","type":"iframe"},{"url":"https://apps.use2.us-gov-pure.cloud/genesys-bootstrap/hub.html","type":"iframe"},{"url":"https://apps.use2.us-gov-pure.cloud/messenger/messenger.html","type":"iframe"},{"url":"https://apps.use2.us-gov-pure.cloud/messenger/messenger-renderer.html","type":"iframe"}]},"images":{"engine":"images","count":2,"images":[{"src":"https://frontend.medicare.gov/assets/medicare-logo-green-DrWAB2BY.svg","alt":"Medicare.gov","hasAlt":true,"isDecorative":false,"isMissingAlt":false,"ariaHidden":false,"rolePresentation":false,"renderedWidth":171,"renderedHeight":25,"naturalWidth":300,"naturalHeight":44,"loading":null,"decoding":null,"altVerdict":"GOOD","altReason":"present, no red flags","bytes":4732},{"src":"https://bat.bing.com/action/0?ti=97143892&Ver=2&mid=67287f04-1f4d-4758-b793-89ae0005f18b&bo=1&sid=4714f2d083f311f180aae1ed0c3ec03d&vid=4715108083f311f18b3d711917a3526a&vids=0&msclkid=N&uach=pv%3D&pi=0&lg=en-US&sw=1280&sh=800&sc=24&nwd=1&tl=Assessments%20%26%20care%20plans%20in%20Skilled%20Nursing%20Facilities%20%7C%20Medicare&p=https%3A%2F%2Fwww.medicare.gov%2Fproviders-services%2Foriginal-medicare%2Fskilled-nursing%2Fassessments-care-plans&r=&lt=575&evt=pageLoad&sv=2&cdb=AQwR&rn=10914","alt":"","hasAlt":true,"isDecorative":true,"isMissingAlt":false,"ariaHidden":false,"rolePresentation":false,"renderedWidth":null,"renderedHeight":null,"naturalWidth":null,"naturalHeight":null,"loading":null,"decoding":null,"altVerdict":"DECORATIVE","altReason":"alt=\"\" (decorative)","bytes":null}]},"publicInterest":{"engine":"public-interest","checkedAt":"2026-07-20T04:28:17.733Z","a11yStatement":{"result":"pass","url":"https://www.medicare.gov/about-us/accessibility-nondiscrimination-notice","confidence":"medium","checkedAt":"2026-07-20T04:28:17.007Z"},"carbonTxt":{"result":"fail","url":null,"valid":false,"fields":{},"checkedAt":"2026-07-20T04:28:17.008Z"},"greenWebFoundation":{"result":"fail","green":false,"hostedBy":null,"url":"https://api.thegreenwebfoundation.org/greencheck/medicare.gov","checkedAt":"2026-07-20T04:28:17.009Z"},"sitemaps":{"xml":{"found":true,"url":"https://www.medicare.gov/sitemap.xml"},"human":{"found":true,"url":"https://www.medicare.gov/sitemap"},"checkedAt":"2026-07-20T04:28:17.010Z"}}}